zigate/__init__.py
zigate/adminpanel.py
zigate/broker.py
zigate/clusters.py
zigate/const.py
zigate/core.py
zigate/firmware.py
zigate/flasher.py
zigate/ikea_ota_download.py
zigate/mqtt_broker.py
zigate/responses.py
zigate/transport.py
zigate/version.py
zigate/templates/CLA60_RGBW_OSRAM.json
zigate/templates/TRADFRI_bulb_E27_W_opal_1000lm.json
zigate/templates/lumi.ctrl_neutral1.json
zigate/templates/lumi.ctrl_neutral2.json
zigate/templates/lumi.remote.b186acn01.json
zigate/templates/lumi.remote.b286acn01.json
zigate/templates/lumi.sens.json
zigate/templates/lumi.sensor_86sw2.json
zigate/templates/lumi.sensor_cube.aqgl01.json
zigate/templates/lumi.sensor_cube.json
zigate/templates/lumi.sensor_ht.json
zigate/templates/lumi.sensor_magnet.aq2.json
zigate/templates/lumi.sensor_magnet.json
zigate/templates/lumi.sensor_motion.aq2.json
zigate/templates/lumi.sensor_switch.aq2.json
zigate/templates/lumi.sensor_wleak.aq1.json
zigate/templates/lumi.vibration.aq1.json
zigate/templates/lumi.weather.json
zigate-0.33.1.dist-info/LICENSE
zigate-0.33.1.dist-info/METADATA
zigate-0.33.1.dist-info/WHEEL
zigate-0.33.1.dist-info/top_level.txt
zigate-0.33.1.dist-info/RECORD
