Metadata-Version: 2.1
Name: zigate
Version: 0.33.1
Summary: python library for the zigate gateway (zigbee) http://zigate.fr
Home-page: https://github.com/doudz/zigate
Author: Sébastien RAMAGE
Author-email: sebastien.ramage@gmail.com
License: UNKNOWN
Project-URL: Bug Reports, https://github.com/doudz/zigate/issues
Project-URL: Source, https://github.com/doudz/zigate/
Keywords: zigate zigbee python3
Platform: UNKNOWN
Classifier: Development Status :: 5 - Production/Stable
Classifier: Intended Audience :: Developers
Classifier: Programming Language :: Python :: 3
Classifier: License :: OSI Approved :: MIT License
Classifier: Natural Language :: English
Requires-Python: >=3
Requires-Dist: bottle
Requires-Dist: pydispatcher
Requires-Dist: pyserial
Requires-Dist: requests
Provides-Extra: dev
Requires-Dist: tox ; extra == 'dev'
Provides-Extra: gpio
Requires-Dist: RPi.GPIO ; extra == 'gpio'
Provides-Extra: mqtt
Requires-Dist: paho-mqtt ; extra == 'mqtt'
